rtl/fifo.v
// MIT License
//
// Copyright (c) 2021 Instituto Nacional de Astrofísica, Óptica y Electrónica.
//
// Permission is hereby granted, free of charge, to any person obtaining a copy
// of this software and associated documentation files (the "Software"), to deal
// in the Software without restriction, including without limitation the rights
// to use, copy, modify, merge, publish, distribute, sublicense, and/or sell
// copies of the Software, and to permit persons to whom the Software is
// furnished to do so, subject to the following conditions:
//
// The above copyright notice and this permission notice shall be included in all
// copies or substantial portions of the Software.

// THE SOFTWARE IS PROVIDED "AS IS", WITHOUT WARRANTY OF ANY KIND, EXPRESS OR
// IMPLIED, INCLUDING BUT NOT LIMITED TO THE WARRANTIES OF MERCHANTABILITY,
// FITNESS FOR A PARTICULAR PURPOSE AND NONINFRINGEMENT. IN NO EVENT SHALL THE
// AUTHORS OR COPYRIGHT HOLDERS BE LIABLE FOR ANY CLAIM, DAMAGES OR OTHER
// LIABILITY, WHETHER IN AN ACTION OF CONTRACT, TORT OR OTHERWISE, ARISING FROM,
// OUT OF OR IN CONNECTION WITH THE SOFTWARE OR THE USE OR OTHER DEALINGS IN THE
// SOFTWARE.
////////////////////////////////////////////////////////////////////////////////
// Filename: fifo.v
//
// Project: Fast Walsh-Haddamard Transform
//
// Description: FIFO Design to the Delay Line in the butterfly module
//
// Author: Andrés M. Manjarrés
////////////////////////////////////////////////////////////////////////////////
module fifo (i_clk, i_wr, i_data, i_rd,  o_data );
  parameter WIDTH = 8; //Bits per element
  parameter M_WIDTH  = 8; //FIFO_Size = M = 2^(M_WIDTH)

  input wire i_clk;
  input wire i_wr;
  input wire [(WIDTH-1):0] i_data;
  input wire i_rd;
  output reg [(WIDTH-1):0] o_data;
  reg o_full;
  reg o_empty;


  reg [(WIDTH-1):0] fifo_mem [0:(1<<M_WIDTH)-1]; //FIFO Memory

  wire w_wr = (i_wr && !o_full); //write_data signal (avoid to write a Full FIFO)
  wire w_rd = i_rd &&!o_empty;   //read_data signal (avoid to read a empty FIFO)

  /* Write to the FIFO memory */
  reg [M_WIDTH:0] wr_addr; //write pointer
  reg [M_WIDTH:0] rd_addr;
  initial rd_addr = 0;
  initial wr_addr = 0;

  always @ (posedge i_clk) begin
    if (w_wr)
        wr_addr <= wr_addr + 1;
    if (w_rd)
        rd_addr <= rd_addr + 1;
  end

  always @ (posedge i_clk) begin
    if (w_wr)
        fifo_mem[wr_addr[M_WIDTH-1:0]] <= i_data;
    if (w_rd)
        o_data <= fifo_mem[rd_addr[M_WIDTH-1:0]];
  end

  ///  Output Flags
  reg [M_WIDTH:0] o_fill;
  always @ (*)
    o_fill = wr_addr - rd_addr;
  always @ (*)
    o_empty = (o_fill == 0);
  always @ (*)
    o_full = (o_fill == {1'b1,{(M_WIDTH){1'b0}} });

endmodule // fifo

rtl/diff2d.v

module diff2d(i_clk, i_reset, i_data, i_start, o_datax, o_datay, o_address, o_Dx_addr, o_DyValid, o_DxValid, o_bussy);
  parameter WIDTH = 32, ADD_W = 12;
  localparam l = 6; //log2(px); px =64
  input  wire                      i_clk;
  input  wire                      i_reset;
  input  wire signed [(WIDTH-1):0] i_data;
  input  wire                      i_start;
  output wire signed [(WIDTH-1):0] o_datax;
  output wire signed [(WIDTH-1):0] o_datay;
  output wire        [(ADD_W-1):0] o_address;
  output wire        [(ADD_W-1):0] o_Dx_addr;
  output wire                      o_DyValid;
  output wire                      o_DxValid;
  output wire                      o_bussy;
  //////////////////////////////////////////////////////////////////////////////
  // Registers and wires
  //////////////////////////////////////////////////////////////////////////////
  reg  signed [(WIDTH-1):0] r_datax;
  reg  signed [(WIDTH-1):0] r_datay;
  reg  signed [(WIDTH-1):0] r_DyOp1; //First operand
  reg  signed [(WIDTH-1):0] r_DyOp2; //Second operand
  reg  signed [(WIDTH-1):0] r_DyOp0; //First Column operand
  reg  signed [(WIDTH-1):0] r_OutFIFO; //
  reg         [(ADD_W-1):0] counter;
  reg         [(ADD_W-1):0] w_DxAddr;
  reg         [(l-1):0]     column_counter;
  reg         [(l-1):0]     fifo_counter;
  reg                       counter_en;
  reg                       column_en;
  reg                       r_DyValid;
  reg                       r_DxValid;
  reg                       DyOp1_en;
  reg                       DyOp2_en;
  reg                       datay_en;
  reg                       datax_en;
  reg                       FIFO_wr;
  reg                       FIFO_rd;
  reg                       r_bussy;
  wire                      full_FIFO;
  wire signed [(WIDTH-1):0] w_op1; //First operand multiplexor


  always @ (posedge i_clk) begin
    if(DyOp1_en)
      r_DyOp1 <= i_data;
  end
  always @ (posedge i_clk) begin
    if(&column_counter) //column_counter == 0;
      r_DyOp0 <= r_DyOp1;
  end
  always @ (posedge i_clk) begin
    if(DyOp2_en)
      r_DyOp2 <= r_DyOp1;
  end
  /// To Do:
  //        * El IDLE debe ser mas un reset de los conadores y del FIFO para el Todo anterior.
 assign FIFO_wr = DyOp2_en;
  fifo  #(.WIDTH(WIDTH), .M_WIDTH(l))
          f0(i_clk, FIFO_wr, r_DyOp1, FIFO_rd,  r_OutFIFO);

  assign w_op1 = (&column_counter) ? r_DyOp0 : r_DyOp1; //column_counter == px-1

  always @ (posedge i_clk) begin
    if(datay_en)
      r_datay <= w_op1-r_DyOp2;
  end
  always @ (posedge i_clk) begin
    if(datax_en)
      r_datax <= r_DyOp1-r_OutFIFO;
  end

  always @ (posedge i_clk) begin
    if (counter_en) begin
      counter <= counter+1;
    end
  end
  always @ (posedge i_clk) begin
    if (column_en) begin
      column_counter <= column_counter+1;
    end
  end
  always @ (posedge i_clk) begin
    if (DyOp1_en) begin
      fifo_counter <= fifo_counter+1;
    end
  end
  assign full_FIFO = &fifo_counter; //column_counter start one clock cycle before the fifo_wr signal and can predict the full_fifo signal.
  always @ (posedge i_clk) begin
    if (datax_en) begin
      w_DxAddr <= w_DxAddr+1;
    end
  end
  //////////////////////////////////////////////////////////////////////////////
  // Control (FSM)
  //////////////////////////////////////////////////////////////////////////////
  localparam IDLE  = 4'b0000; //IDLE state
  localparam S1    = 4'b0001; //Save Input 1 **(Dy)**
  localparam S2    = 4'b0010; //Save Input 2 **(Dy)** and Write FIFO
  localparam S3    = 4'b0011; //Write FIFO
  localparam S4    = 4'b0100; //Read FIFO
  localparam S5    = 4'b0101; //Save Input 2 **(Dx)**
  localparam S6    = 4'b0110; //Wait and save results
  localparam S7    = 4'b0111; //Save last Input 2 **(Dy)**
  localparam S8    = 4'b1000; //Save last Result **(Dy)**
  localparam S9    = 4'b1001; //Wait And save results
  localparam S10   = 4'b1010; //Save last Input 2 (Dx)
  localparam S11   = 4'b1011; //Save last Result (Dx)
  localparam S12   = 4'b1100; //Save last Result (Dx)
  reg [3:0] state = IDLE;
  always @(posedge i_clk)
    if (i_reset) begin
      state <= IDLE;
    end
    else
      case (state)
        IDLE : begin
          if (i_start)
            state <= S1;
          else
            state <= IDLE;
        end
        S1 : begin
            state <= S2;
        end
        S2 : begin
            state <= S3;
        end
        S3 : begin
          state <= S4;
        end
        S4 : begin
          if (full_FIFO)
            state <= S5;
          else
            state <= S4;
        end
        S5 : begin
          state <= S6;
        end
        S6 : begin
          state <= S7;
        end
        S7 : begin
          if (&counter)
            state <= S8;
          else
            state <= S7;
        end
        S8 : begin
          state <= S9;
        end
        S9 : begin
          state <= S10;
        end
        S10 : begin
          if (&column_counter)
            state <= S11;
          else
            state <= S10;
        end
        S11 : begin
          state <= S12;
        end
        S12 : begin
          state <= IDLE;
        end
        default : begin  // Fault Recovery
          state <= IDLE;
        end
      endcase
/* verilator lint_off COMBDLY */
  always @(*)
    case (state)
      IDLE : begin
        r_bussy    <= 1'b0;
        counter_en <= 1'b0;
        column_en  <= 1'b0;
        DyOp1_en   <= 1'b0;
        DyOp2_en   <= 1'b0;
        datay_en   <= 1'b0;
        datax_en   <= 1'b0;
        FIFO_rd    <= 1'b0;
      end
      S1 : begin
        r_bussy    <= 1'b1;
        counter_en <= 1'b1;
        column_en  <= 1'b0;
        DyOp1_en   <= 1'b0;
        DyOp2_en   <= 1'b0;
        datay_en   <= 1'b0;
        datax_en   <= 1'b0;
        FIFO_rd    <= 1'b0;
      end
      S2 : begin
        r_bussy    <= 1'b1;
        counter_en <= 1'b1;
        column_en  <= 1'b0;
        DyOp1_en   <= 1'b1;
        DyOp2_en   <= 1'b0;
        datay_en   <= 1'b0;
        datax_en   <= 1'b0;
        FIFO_rd    <= 1'b0;
      end
      S3 : begin
        r_bussy    <= 1'b1;
        counter_en <= 1'b1;
        column_en  <= 1'b0;
        DyOp1_en   <= 1'b1;
        DyOp2_en   <= 1'b1;
        datay_en   <= 1'b0;
        datax_en   <= 1'b0;
        FIFO_rd    <= 1'b0;
      end
      S4 : begin
        r_bussy    <= 1'b1;
        counter_en <= 1'b1;
        column_en  <= 1'b1;
        DyOp1_en   <= 1'b1;
        DyOp2_en   <= 1'b1;
        datay_en   <= 1'b1;
        datax_en   <= 1'b0;
        FIFO_rd    <= 1'b0;
      end
      S5 : begin
        r_bussy    <= 1'b1;
        counter_en <= 1'b1;
        column_en  <= 1'b1;
        DyOp1_en   <= 1'b1;
        DyOp2_en   <= 1'b1;
        datay_en   <= 1'b1;
        datax_en   <= 1'b0;
        FIFO_rd    <= 1'b1;
      end
      S6 : begin
        r_bussy    <= 1'b1;
        counter_en <= 1'b1;
        column_en  <= 1'b1;
        DyOp1_en   <= 1'b1;
        DyOp2_en   <= 1'b1;
        datay_en   <= 1'b1;
        datax_en   <= 1'b1;
        FIFO_rd    <= 1'b1;
      end
      S7 : begin
        r_bussy    <= 1'b1;
        counter_en <= 1'b1;
        column_en  <= 1'b1;
        DyOp1_en   <= 1'b1;
        DyOp2_en   <= 1'b1;
        datay_en   <= 1'b1;
        datax_en   <= 1'b1;
        FIFO_rd    <= 1'b1;
      end
      S8 : begin
        r_bussy    <= 1'b1;
        counter_en <= 1'b1;
        column_en  <= 1'b1;
        DyOp1_en   <= 1'b1;
        DyOp2_en   <= 1'b1;
        datay_en   <= 1'b1;
        datax_en   <= 1'b1;
        FIFO_rd    <= 1'b1;
      end
      S9 : begin
        r_bussy    <= 1'b1;
        counter_en <= 1'b1;
        column_en  <= 1'b1;
        DyOp1_en   <= 1'b1;
        DyOp2_en   <= 1'b0;
        datay_en   <= 1'b1;
        datax_en   <= 1'b1;
        FIFO_rd    <= 1'b1;
      end
      S10 : begin
        r_bussy    <= 1'b1;
        counter_en <= 1'b1;
        column_en  <= 1'b1;
        DyOp1_en   <= 1'b1;
        DyOp2_en   <= 1'b0;
        datay_en   <= 1'b0;
        datax_en   <= 1'b1;
        FIFO_rd    <= 1'b1;
      end
      S11 : begin
        r_bussy    <= 1'b1;
        counter_en <= 1'b0;
        column_en  <= 1'b0;
        DyOp1_en   <= 1'b0;
        DyOp2_en   <= 1'b0;
        datay_en   <= 1'b0;
        datax_en   <= 1'b1;
        FIFO_rd    <= 1'b1;
      end
      S12 : begin
        r_bussy    <= 1'b1;
        counter_en <= 1'b0;
        column_en  <= 1'b0;
        DyOp1_en   <= 1'b0;
        DyOp2_en   <= 1'b0;
        datay_en   <= 1'b0;
        datax_en   <= 1'b1;
        FIFO_rd    <= 1'b0;
      end
      default : begin
        r_bussy    <= 1'b0;
        counter_en <= 1'b0;
        column_en  <= 1'b0;
        DyOp1_en   <= 1'b0;
        DyOp2_en   <= 1'b0;
        datay_en   <= 1'b0;
        datax_en   <= 1'b0;
        FIFO_rd    <= 1'b0;
      end
    endcase
/* verilator lint_on COMBDLY */
  always @ (posedge i_clk) begin
    r_DyValid <= datay_en;
    r_DxValid <= datax_en;
  end
  //////////////////////////////////////////////////////////////////////////////
  // Output logic
  //////////////////////////////////////////////////////////////////////////////
  assign o_datax   = r_datax;
  assign o_datay   = r_datay;
  assign o_address = counter;
  assign o_Dx_addr = w_DxAddr;
  assign o_DyValid = r_DyValid;
  assign o_DxValid = r_DxValid;
  assign o_bussy   = r_bussy;

endmodule // diff_2d

rtl/rom.v
module rom(
    input  wire         clk,
    input  wire  [11:0] addr,
    output reg   [31:0] data
    );

    reg [31:0] memory [4095:0];

    initial begin
        $display("Creating rom_sync from init file '%s'.", "U_fixed_point.mem");
        $readmemh("U_fixed_point.mem", memory);
    end

    always @(posedge clk) begin
        data <= memory[addr];
    end
endmodule

rtl/top.v
/* verilator lint_off UNUSED */
module top(i_clk, i_reset, i_start, o_valid, o_datax, o_datay);
  input  wire        i_clk;
  input  wire        i_reset;
  input  wire        i_start;
  output wire        o_valid;
  output wire [31:0] o_datax;
  output wire [31:0] o_datay;
  ///register an wires
  wire signed [31:0] w_data;
  wire signed [11:0] w_address;
  wire signed [11:0] w_Dxaddr;
  wire               w_bussy;
  wire               w_DxValid;
  wire               w_DyValid;

  rom rom_int(i_clk, w_address, w_data);

  diff2d #(.WIDTH(32), .ADD_W(12))
         diff2d_inst(i_clk, i_reset, w_data, i_start, o_datax, o_datay, w_address, w_Dxaddr, w_DyValid, w_DxValid, w_bussy);

  assign o_valid = w_DxValid;

endmodule // top
/* verilator lint_on UNUSED */

top_trace.vcd
$version Generated by VerilatedVcd $end
$date Mon Apr 26 12:14:35 2021
 $end
$timescale   1ns $end

 $scope module TOP $end
  $var wire  1 B i_clk $end
  $var wire  1 C i_reset $end
  $var wire  1 D i_start $end
  $var wire 32 F o_datax [31:0] $end
  $var wire 32 G o_datay [31:0] $end
  $var wire  1 E o_valid $end
  $scope module top $end
   $var wire  1 B i_clk $end
   $var wire  1 C i_reset $end
   $var wire  1 D i_start $end
   $var wire 32 F o_datax [31:0] $end
   $var wire 32 G o_datay [31:0] $end
   $var wire  1 E o_valid $end
   $var wire  1 6 w_DxValid $end
   $var wire 12 5 w_Dxaddr [11:0] $end
   $var wire  1 7 w_DyValid $end
   $var wire 12 4 w_address [11:0] $end
   $var wire  1 # w_bussy $end
   $var wire 32 3 w_data [31:0] $end
   $scope module diff2d_inst $end
    $var wire 32 I ADD_W [31:0] $end
    $var wire  1 & DyOp1_en $end
    $var wire  1 ' DyOp2_en $end
    $var wire  1 * FIFO_rd $end
    $var wire  1 ' FIFO_wr $end
    $var wire  4 K IDLE [3:0] $end
    $var wire  4 L S1 [3:0] $end
    $var wire  4 U S10 [3:0] $end
    $var wire  4 V S11 [3:0] $end
    $var wire  4 W S12 [3:0] $end
    $var wire  4 M S2 [3:0] $end
    $var wire  4 N S3 [3:0] $end
    $var wire  4 O S4 [3:0] $end
    $var wire  4 P S5 [3:0] $end
    $var wire  4 Q S6 [3:0] $end
    $var wire  4 R S7 [3:0] $end
    $var wire  4 S S8 [3:0] $end
    $var wire  4 T S9 [3:0] $end
    $var wire 32 H WIDTH [31:0] $end
    $var wire  6 > column_counter [5:0] $end
    $var wire  1 % column_en $end
    $var wire 12 4 counter [11:0] $end
    $var wire  1 $ counter_en $end
    $var wire  1 ) datax_en $end
    $var wire  1 ( datay_en $end
    $var wire  6 ? fifo_counter [5:0] $end
    $var wire  1 @ full_FIFO $end
    $var wire  1 B i_clk $end
    $var wire 32 3 i_data [31:0] $end
    $var wire  1 C i_reset $end
    $var wire  1 D i_start $end
    $var wire 32 J l [31:0] $end
    $var wire  1 6 o_DxValid $end
    $var wire 12 5 o_Dx_addr [11:0] $end
    $var wire  1 7 o_DyValid $end
    $var wire 12 4 o_address [11:0] $end
    $var wire  1 # o_bussy $end
    $var wire 32 F o_datax [31:0] $end
    $var wire 32 G o_datay [31:0] $end
    $var wire  1 6 r_DxValid $end
    $var wire 32 < r_DyOp0 [31:0] $end
    $var wire 32 : r_DyOp1 [31:0] $end
    $var wire 32 ; r_DyOp2 [31:0] $end
    $var wire  1 7 r_DyValid $end
    $var wire 32 = r_OutFIFO [31:0] $end
    $var wire  1 # r_bussy $end
    $var wire 32 8 r_datax [31:0] $end
    $var wire 32 9 r_datay [31:0] $end
    $var wire  4 + state [3:0] $end
    $var wire 12 5 w_DxAddr [11:0] $end
    $var wire 32 A w_op1 [31:0] $end
    $scope module f0 $end
     $var wire 32 J M_WIDTH [31:0] $end
     $var wire 32 H WIDTH [31:0] $end
     $var wire  1 B i_clk $end
     $var wire 32 : i_data [31:0] $end
     $var wire  1 * i_rd $end
     $var wire  1 ' i_wr $end
     $var wire 32 = o_data [31:0] $end
     $var wire  1 - o_empty $end
     $var wire  7 2 o_fill [6:0] $end
     $var wire  1 , o_full $end
     $var wire  7 1 rd_addr [6:0] $end
     $var wire  1 / w_rd $end
     $var wire  1 . w_wr $end
     $var wire  7 0 wr_addr [6:0] $end
    $upscope $end
   $upscope $end
   $scope module rom_int $end
    $var wire 12 4 addr [11:0] $end
    $var wire  1 B clk $end
    $var wire 32 3 data [31:0] $end
   $upscope $end
  $upscope $end
 $upscope $end
$enddefinitions $end


#8
0#
0$
0%
0&
0'
0(
0)
0*
b0000 +
0,
1-
0.
0/
b0000000 0
b0000000 1
b0000000 2
b00000000000000000000000000000000 3
b000000000000 4
b000000000000 5
06
07
b00000000000000000000000000000000 8
b00000000000000000000000000000000 9
b00000000000000000000000000000000 :
b00000000000000000000000000000000 ;
b00000000000000000000000000000000 <
b00000000000000000000000000000000 =
b000000 >
b000000 ?
0@
b00000000000000000000000000000000 A
0B
0C
0D
0E
b00000000000000000000000000000000 F
b00000000000000000000000000000000 G
b00000000000000000000000000100000 H
b00000000000000000000000000001100 I
b00000000000000000000000000000110 J
b0000 K
b0001 L
b0010 M
b0011 N
b0100 O
b0101 P
b0110 Q
b0111 R
b1000 S
b1001 T
b1010 U
b1011 V
b1100 W
#10
1B
#15
0B
#18
1C
#20
1B
#25
0B
#28
0C
#30
1B
#35
0B
#38
#40
1B
#45
0B
#48
1D
#50
1#
1$
b0001 +
1B
#55
0B
#58
0D
#60
1&
b0010 +
b000000000001 4
1B
#65
0B
#68
#70
1'
b0011 +
1.
b000000000010 4
b000001 ?
1B
#75
0B
#78
#80
1%
1(
b0100 +
0-
b0000001 0
b0000001 2
b000000000011 4
b000010 ?
1B
#85
0B
#88
#90
b0000010 0
b0000010 2
b000000000100 4
17
b000001 >
b000011 ?
1B
#95
0B
#98
#100
b0000011 0
b0000011 2
b000000000101 4
b000010 >
b000100 ?
1B
#105
0B
#108
#110
b0000100 0
b0000100 2
b000000000110 4
b000011 >
b000101 ?
1B
#115
0B
#118
#120
b0000101 0
b0000101 2
b000000000111 4
b000100 >
b000110 ?
1B
#125
0B
#128
#130
b0000110 0
b0000110 2
b000000001000 4
b000101 >
b000111 ?
1B
#135
0B
#138
#140
b0000111 0
b0000111 2
b000000001001 4
b000110 >
b001000 ?
1B
#145
0B
#148
#150
b0001000 0
b0001000 2
b000000001010 4
b000111 >
b001001 ?
1B
#155
0B
#158
#160
b0001001 0
b0001001 2
b000000001011 4
b001000 >
b001010 ?
1B
#165
0B
#168
#170
b0001010 0
b0001010 2
b000000001100 4
b001001 >
b001011 ?
1B
#175
0B
#178
#180
b0001011 0
b0001011 2
b000000001101 4
b001010 >
b001100 ?
1B
#185
0B
#188
#190
b0001100 0
b0001100 2
b000000001110 4
b001011 >
b001101 ?
1B
#195
0B
#198
#200
b0001101 0
b0001101 2
b000000001111 4
b001100 >
b001110 ?
1B
#205
0B
#208
#210
b0001110 0
b0001110 2
b000000010000 4
b001101 >
b001111 ?
1B
#215
0B
#218
#220
b0001111 0
b0001111 2
b000000010001 4
b001110 >
b010000 ?
1B
#225
0B
#228
#230
b0010000 0
b0010000 2
b000000010010 4
b001111 >
b010001 ?
1B
#235
0B
#238
#240
b0010001 0
b0010001 2
b000000010011 4
b010000 >
b010010 ?
1B
#245
0B
#248
#250
b0010010 0
b0010010 2
b000000010100 4
b010001 >
b010011 ?
1B
#255
0B
#258
#260
b0010011 0
b0010011 2
b000000010101 4
b010010 >
b010100 ?
1B
#265
0B
#268
#270
b0010100 0
b0010100 2
b000000010110 4
b010011 >
b010101 ?
1B
#275
0B
#278
#280
b0010101 0
b0010101 2
b000000010111 4
b010100 >
b010110 ?
1B
#285
0B
#288
#290
b0010110 0
b0010110 2
b000000011000 4
b010101 >
b010111 ?
1B
#295
0B
#298
#300
b0010111 0
b0010111 2
b000000011001 4
b010110 >
b011000 ?
1B
#305
0B
#308
#310
b0011000 0
b0011000 2
b000000011010 4
b010111 >
b011001 ?
1B
#315
0B
#318
#320
b0011001 0
b0011001 2
b000000011011 4
b011000 >
b011010 ?
1B
#325
0B
#328
#330
b0011010 0
b0011010 2
b000000011100 4
b011001 >
b011011 ?
1B
#335
0B
#338
#340
b0011011 0
b0011011 2
b000000011101 4
b011010 >
b011100 ?
1B
#345
0B
#348
#350
b0011100 0
b0011100 2
b000000011110 4
b011011 >
b011101 ?
1B
#355
0B
#358
#360
b0011101 0
b0011101 2
b000000011111 4
b011100 >
b011110 ?
1B
#365
0B
#368
#370
b0011110 0
b0011110 2
b000000100000 4
b011101 >
b011111 ?
1B
#375
0B
#378
#380
b0011111 0
b0011111 2
b000000100001 4
b011110 >
b100000 ?
1B
#385
0B
#388
#390
b0100000 0
b0100000 2
b000000100010 4
b011111 >
b100001 ?
1B
#395
0B
#398
#400
b0100001 0
b0100001 2
b000000100011 4
b100000 >
b100010 ?
1B
#405
0B
#408
#410
b0100010 0
b0100010 2
b000000100100 4
b100001 >
b100011 ?
1B
#415
0B
#418
#420
b0100011 0
b0100011 2
b000000100101 4
b100010 >
b100100 ?
1B
#425
0B
#428
#430
b0100100 0
b0100100 2
b000000100110 4
b100011 >
b100101 ?
1B
#435
0B
#438
#440
b0100101 0
b0100101 2
b000000100111 4
b100100 >
b100110 ?
1B
#445
0B
#448
#450
b0100110 0
b0100110 2
b000000101000 4
b100101 >
b100111 ?
1B
#455
0B
#458
#460
b0100111 0
b0100111 2
b000000101001 4
b100110 >
b101000 ?
1B
#465
0B
#468
#470
b0101000 0
b0101000 2
b000000101010 4
b100111 >
b101001 ?
1B
#475
0B
#478
#480
b0101001 0
b0101001 2
b000000101011 4
b101000 >
b101010 ?
1B
#485
0B
#488
#490
b0101010 0
b0101010 2
b000000101100 4
b101001 >
b101011 ?
1B
#495
0B
#498
#500
b0101011 0
b0101011 2
b000000101101 4
b101010 >
b101100 ?
1B
#505
0B
#508
#510
b0101100 0
b0101100 2
b000000101110 4
b101011 >
b101101 ?
1B
#515
0B
#518
#520
b0101101 0
b0101101 2
b000000101111 4
b101100 >
b101110 ?
1B
#525
0B
#528
#530
b0101110 0
b0101110 2
b000000110000 4
b101101 >
b101111 ?
1B
#535
0B
#538
#540
b0101111 0
b0101111 2
b000000110001 4
b101110 >
b110000 ?
1B
#545
0B
#548
#550
b0110000 0
b0110000 2
b000000110010 4
b101111 >
b110001 ?
1B
#555
0B
#558
#560
b0110001 0
b0110001 2
b000000110011 4
b110000 >
b110010 ?
1B
#565
0B
#568
#570
b0110010 0
b0110010 2
b000000110100 4
b110001 >
b110011 ?
1B
#575
0B
#578
#580
b0110011 0
b0110011 2
b000000110101 4
b110010 >
b110100 ?
1B
#585
0B
#588
#590
b0110100 0
b0110100 2
b000000110110 4
b110011 >
b110101 ?
1B
#595
0B
#598
#600
b0110101 0
b0110101 2
b000000110111 4
b110100 >
b110110 ?
1B
#605
0B
#608
#610
b0110110 0
b0110110 2
b000000111000 4
b110101 >
b110111 ?
1B
#615
0B
#618
#620
b0110111 0
b0110111 2
b000000111001 4
b110110 >
b111000 ?
1B
#625
0B
#628
#630
b0111000 0
b0111000 2
b000000111010 4
b110111 >
b111001 ?
1B
#635
0B
#638
#640
b0111001 0
b0111001 2
b000000111011 4
b111000 >
b111010 ?
1B
#645
0B
#648
#650
b0111010 0
b0111010 2
b000000111100 4
b111001 >
b111011 ?
1B
#655
0B
#658
#660
b0111011 0
b0111011 2
b000000111101 4
b111010 >
b111100 ?
1B
#665
0B
#668
#670
b0111100 0
b0111100 2
b000000111110 4
b111011 >
b111101 ?
1B
#675
0B
#678
#680
b0111101 0
b0111101 2
b000000111111 4
b111100 >
b111110 ?
1B
#685
0B
#688
#690
b0111110 0
b0111110 2
b000001000000 4
b111101 >
b111111 ?
1@
1B
#695
0B
#698
#700
1*
b0101 +
1/
b0111111 0
b0111111 2
b000001000001 4
b111110 >
b000000 ?
0@
1B
#705
0B
#708
#710
1)
b0110 +
b1000000 0
b0000001 1
b000001000010 4
b111111 >
b000001 ?
1B
#715
0B
#718
#720
b0111 +
b1000001 0
b0000010 1
b000001000011 4
b000000000001 5
16
b000000 >
b000010 ?
1B
1E
#725
0B
#728
#730
b1000010 0
b0000011 1
b000001000100 4
b000000000010 5
b000001 >
b000011 ?
1B
#735
0B
#738
#740
b1000011 0
b0000100 1
b000001000101 4
b000000000011 5
b000010 >
b000100 ?
1B
#745
0B
#748
#750
b1000100 0
b0000101 1
b000001000110 4
b000000000100 5
b000011 >
b000101 ?
1B
#755
0B
#758
#760
b1000101 0
b0000110 1
b000001000111 4
b000000000101 5
b000100 >
b000110 ?
1B
#765
0B
#768
#770
b1000110 0
b0000111 1
b000001001000 4
b000000000110 5
b000101 >
b000111 ?
1B
#775
0B
#778
#780
b1000111 0
b0001000 1
b000001001001 4
b000000000111 5
b000110 >
b001000 ?
1B
#785
0B
#788
#790
b1001000 0
b0001001 1
b000001001010 4
b000000001000 5
b000111 >
b001001 ?
1B
#795
0B
#798
#800
b1001001 0
b0001010 1
b000001001011 4
b000000001001 5
b001000 >
b001010 ?
1B
#805
0B
#808
#810
b1001010 0
b0001011 1
b000001001100 4
b000000001010 5
b001001 >
b001011 ?
1B
#815
0B
#818
#820
b1001011 0
b0001100 1
b000001001101 4
b000000001011 5
b001010 >
b001100 ?
1B
#825
0B
#828
#830
b1001100 0
b0001101 1
b000001001110 4
b000000001100 5
b001011 >
b001101 ?
1B
#835
0B
#838
#840
b1001101 0
b0001110 1
b000001001111 4
b000000001101 5
b001100 >
b001110 ?
1B
#845
0B
#848
#850
b1001110 0
b0001111 1
b000001010000 4
b000000001110 5
b001101 >
b001111 ?
1B
#855
0B
#858
#860
b1001111 0
b0010000 1
b000001010001 4
b000000001111 5
b001110 >
b010000 ?
1B
#865
0B
#868
#870
b1010000 0
b0010001 1
b000001010010 4
b000000010000 5
b001111 >
b010001 ?
1B
#875
0B
#878
#880
b1010001 0
b0010010 1
b000001010011 4
b000000010001 5
b010000 >
b010010 ?
1B
#885
0B
#888
#890
b1010010 0
b0010011 1
b000001010100 4
b000000010010 5
b010001 >
b010011 ?
1B
#895
0B
#898
#900
b1010011 0
b0010100 1
b000001010101 4
b000000010011 5
b010010 >
b010100 ?
1B
#905
0B
#908
#910
b1010100 0
b0010101 1
b000001010110 4
b000000010100 5
b010011 >
b010101 ?
1B
#915
0B
#918
#920
b1010101 0
b0010110 1
b000001010111 4
b000000010101 5
b010100 >
b010110 ?
1B
#925
0B
#928
#930
b1010110 0
b0010111 1
b000001011000 4
b000000010110 5
b010101 >
b010111 ?
1B
#935
0B
#938
#940
b1010111 0
b0011000 1
b000001011001 4
b000000010111 5
b010110 >
b011000 ?
1B
#945
0B
#948
#950
b1011000 0
b0011001 1
b000001011010 4
b000000011000 5
b010111 >
b011001 ?
1B
#955
0B
#958
#960
b1011001 0
b0011010 1
b000001011011 4
b000000011001 5
b011000 >
b011010 ?
1B
#965
0B
#968
#970
b1011010 0
b0011011 1
b000001011100 4
b000000011010 5
b011001 >
b011011 ?
1B
#975
0B
#978
#980
b1011011 0
b0011100 1
b000001011101 4
b000000011011 5
b011010 >
b011100 ?
1B
#985
0B
#988
#990
b1011100 0
b0011101 1
b000001011110 4
b000000011100 5
b011011 >
b011101 ?
1B
#995
0B
#998
#1000
b1011101 0
b0011110 1
b000001011111 4
b000000011101 5
b011100 >
b011110 ?
1B
#1005
0B
#1008
#1010
b1011110 0
b0011111 1
b000001100000 4
b000000011110 5
b011101 >
b011111 ?
1B
#1015
0B
#1018
#1020
b1011111 0
b0100000 1
b000001100001 4
b000000011111 5
b011110 >
b100000 ?
1B
#1025
0B
#1028
#1030
b1100000 0
b0100001 1
b000001100010 4
b000000100000 5
b011111 >
b100001 ?
1B
#1035
0B
#1038
#1040
b1100001 0
b0100010 1
b000001100011 4
b000000100001 5
b100000 >
b100010 ?
1B
#1045
0B
#1048
#1050
b1100010 0
b0100011 1
b000001100100 4
b000000100010 5
b100001 >
b100011 ?
1B
#1055
0B
#1058
#1060
b1100011 0
b0100100 1
b000001100101 4
b000000100011 5
b100010 >
b100100 ?
1B
#1065
0B
#1068
#1070
b1100100 0
b0100101 1
b000001100110 4
b000000100100 5
b100011 >
b100101 ?
1B
#1075
0B
#1078
#1080
b1100101 0
b0100110 1
b000001100111 4
b000000100101 5
b100100 >
b100110 ?
1B
#1085
0B
#1088
#1090
b1100110 0
b0100111 1
b000001101000 4
b000000100110 5
b100101 >
b100111 ?
1B
#1095
0B
#1098
#1100
b1100111 0
b0101000 1
b000001101001 4
b000000100111 5
b100110 >
b101000 ?
1B
#1105
0B
#1108
#1110
b1101000 0
b0101001 1
b000001101010 4
b000000101000 5
b100111 >
b101001 ?
1B
#1115
0B
#1118
#1120
b1101001 0
b0101010 1
b000001101011 4
b000000101001 5
b101000 >
b101010 ?
1B
#1125
0B
#1128
#1130
b1101010 0
b0101011 1
b000001101100 4
b000000101010 5
b101001 >
b101011 ?
1B
#1135
0B
#1138
#1140
b1101011 0
b0101100 1
b000001101101 4
b000000101011 5
b101010 >
b101100 ?
1B
#1145
0B
#1148
#1150
b1101100 0
b0101101 1
b000001101110 4
b000000101100 5
b101011 >
b101101 ?
1B
#1155
0B
#1158
#1160
b1101101 0
b0101110 1
b000001101111 4
b000000101101 5
b101100 >
b101110 ?
1B
#1165
0B
#1168
#1170
b1101110 0
b0101111 1
b000001110000 4
b000000101110 5
b101101 >
b101111 ?
1B
#1175
0B
#1178
#1180
b1101111 0
b0110000 1
b000001110001 4
b000000101111 5
b101110 >
b110000 ?
1B
#1185
0B
#1188
